pydantic_sqlalchemy/__init__.py
pydantic_sqlalchemy/main.py
pydantic_sqlalchemy-0.0.8.post1.dist-info/LICENSE
pydantic_sqlalchemy-0.0.8.post1.dist-info/WHEEL
pydantic_sqlalchemy-0.0.8.post1.dist-info/METADATA
pydantic_sqlalchemy-0.0.8.post1.dist-info/RECORD
